{"moduleDefinition":{"range":[1,1,1,26],"value":{"type":"normal","normal":{"moduleName":{"range":[1,8,1,11],"value":["Bob"]},"exposingList":{"range":[1,12,1,26],"value":{"type":"explicit","explicit":[{"range":[1,22,1,25],"value":{"type":"function","function":{"name":"hey"}}}]}}}}},"imports":[{"range":[2,1,2,19],"value":{"moduleName":{"range":[2,8,2,14],"value":["String"]},"moduleAlias":{"range":[2,18,2,19],"value":["S"]},"exposingList":null}},{"range":[3,1,3,17],"value":{"moduleName":{"range":[3,8,3,12],"value":["Char"]},"moduleAlias":{"range":[3,16,3,17],"value":["C"]},"exposingList":null}}],"declarations":[{"range":[6,1,24,1],"value":{"type":"function","function":{"documentation":null,"signature":{"range":[6,1,6,23],"value":{"name":{"range":[6,1,6,4],"value":"hey"},"typeAnnotation":{"range":[6,7,6,23],"value":{"type":"function","function":{"left":{"range":[6,7,6,13],"value":{"type":"typed","typed":{"moduleNameAndName":{"range":[6,7,6,13],"value":{"moduleName":[],"name":"String"}},"args":[]}}},"right":{"range":[6,17,6,23],"value":{"type":"typed","typed":{"moduleNameAndName":{"range":[6,17,6,23],"value":{"moduleName":[],"name":"String"}},"args":[]}}}}}}}},"declaration":{"range":[7,1,24,1],"value":{"name":{"range":[7,1,7,4],"value":"hey"},"arguments":[{"range":[7,5,7,11],"value":{"type":"var","var":{"value":"remark"}}}],"expression":{"range":[9,5,24,1],"value":{"type":"ifBlock","ifBlock":{"clause":{"range":[9,8,9,37],"value":{"type":"application","application":[{"range":[9,8,9,16],"value":{"type":"functionOrValue","functionOrValue":{"moduleName":["S"],"name":"length"}}},{"range":[9,17,9,32],"value":{"type":"parenthesized","parenthesized":{"range":[9,18,9,31],"value":{"type":"application","application":[{"range":[9,18,9,24],"value":{"type":"functionOrValue","functionOrValue":{"moduleName":["S"],"name":"trim"}}},{"range":[9,25,9,31],"value":{"type":"functionOrValue","functionOrValue":{"moduleName":[],"name":"remark"}}}]}}}},{"range":[9,33,9,35],"value":{"type":"operator","operator":"=="}},{"range":[9,36,9,37],"value":{"type":"integer","integer":0}}]}},"then":{"range":[10,9,10,29],"value":{"type":"literal","literal":"Fine. Be that way!"}},"else":{"range":[12,10,24,1],"value":{"type":"ifBlock","ifBlock":{"clause":{"range":[12,13,12,29],"value":{"type":"application","application":[{"range":[12,13,12,22],"value":{"type":"functionOrValue","functionOrValue":{"moduleName":[],"name":"isYelling"}}},{"range":[12,23,12,29],"value":{"type":"functionOrValue","functionOrValue":{"moduleName":[],"name":"remark"}}}]}},"then":{"range":[13,9,18,5],"value":{"type":"ifBlock","ifBlock":{"clause":{"range":[13,12,13,47],"value":{"type":"application","application":[{"range":[13,12,13,27],"value":{"type":"functionOrValue","functionOrValue":{"moduleName":["String"],"name":"endsWith"}}},{"range":[13,28,13,31],"value":{"type":"literal","literal":"?"}},{"range":[13,32,13,47],"value":{"type":"parenthesized","parenthesized":{"range":[13,33,13,46],"value":{"type":"application","application":[{"range":[13,33,13,39],"value":{"type":"functionOrValue","functionOrValue":{"moduleName":["S"],"name":"trim"}}},{"range":[13,40,13,46],"value":{"type":"functionOrValue","functionOrValue":{"moduleName":[],"name":"remark"}}}]}}}}]}},"then":{"range":[14,13,14,48],"value":{"type":"literal","literal":"Calm down, I know what I'm doing!"}},"else":{"range":[16,13,16,31],"value":{"type":"literal","literal":"Whoa, chill out!"}}}}},"else":{"range":[18,10,24,1],"value":{"type":"ifBlock","ifBlock":{"clause":{"range":[18,13,18,48],"value":{"type":"application","application":[{"range":[18,13,18,28],"value":{"type":"functionOrValue","functionOrValue":{"moduleName":["String"],"name":"endsWith"}}},{"range":[18,29,18,32],"value":{"type":"literal","literal":"?"}},{"range":[18,33,18,48],"value":{"type":"parenthesized","parenthesized":{"range":[18,34,18,47],"value":{"type":"application","application":[{"range":[18,34,18,40],"value":{"type":"functionOrValue","functionOrValue":{"moduleName":["S"],"name":"trim"}}},{"range":[18,41,18,47],"value":{"type":"functionOrValue","functionOrValue":{"moduleName":[],"name":"remark"}}}]}}}}]}},"then":{"range":[19,9,19,16],"value":{"type":"literal","literal":"Sure."}},"else":{"range":[22,9,22,20],"value":{"type":"literal","literal":"Whatever."}}}}}}}}}}}}}}}},{"range":[24,1,30,13],"value":{"type":"function","function":{"documentation":null,"signature":{"range":[24,1,24,27],"value":{"name":{"range":[24,1,24,10],"value":"isYelling"},"typeAnnotation":{"range":[24,13,24,27],"value":{"type":"function","function":{"left":{"range":[24,13,24,19],"value":{"type":"typed","typed":{"moduleNameAndName":{"range":[24,13,24,19],"value":{"moduleName":[],"name":"String"}},"args":[]}}},"right":{"range":[24,23,24,27],"value":{"type":"typed","typed":{"moduleNameAndName":{"range":[24,23,24,27],"value":{"moduleName":[],"name":"Bool"}},"args":[]}}}}}}}},"declaration":{"range":[25,1,30,13],"value":{"name":{"range":[25,1,25,10],"value":"isYelling"},"arguments":[{"range":[25,11,25,17],"value":{"type":"var","var":{"value":"remark"}}}],"expression":{"range":[26,5,30,13],"value":{"type":"application","application":[{"range":[26,5,26,10],"value":{"type":"functionOrValue","functionOrValue":{"moduleName":["S"],"name":"any"}}},{"range":[26,11,26,20],"value":{"type":"functionOrValue","functionOrValue":{"moduleName":["C"],"name":"isAlpha"}}},{"range":[26,21,26,27],"value":{"type":"functionOrValue","functionOrValue":{"moduleName":[],"name":"remark"}}},{"range":[27,9,27,11],"value":{"type":"operator","operator":"&&"}},{"range":[27,12,30,13],"value":{"type":"parenthesized","parenthesized":{"range":[27,13,29,35],"value":{"type":"application","application":[{"range":[27,13,27,19],"value":{"type":"functionOrValue","functionOrValue":{"moduleName":[],"name":"remark"}}},{"range":[28,17,28,19],"value":{"type":"operator","operator":"|>"}},{"range":[28,20,28,28],"value":{"type":"functionOrValue","functionOrValue":{"moduleName":["S"],"name":"filter"}}},{"range":[28,29,28,38],"value":{"type":"functionOrValue","functionOrValue":{"moduleName":["C"],"name":"isAlpha"}}},{"range":[29,17,29,19],"value":{"type":"operator","operator":"|>"}},{"range":[29,20,29,25],"value":{"type":"functionOrValue","functionOrValue":{"moduleName":["S"],"name":"all"}}},{"range":[29,26,29,35],"value":{"type":"functionOrValue","functionOrValue":{"moduleName":["C"],"name":"isUpper"}}}]}}}}]}}}}}}}],"comments":[]}